encoderize/__init__.py
encoderize/cli.py
encoderize/visualizers.py
encoderize-0.1.1.dist-info/licenses/LICENSE
encoderize-0.1.1.dist-info/METADATA
encoderize-0.1.1.dist-info/WHEEL
encoderize-0.1.1.dist-info/entry_points.txt
encoderize-0.1.1.dist-info/top_level.txt
encoderize-0.1.1.dist-info/RECORD
