Metadata-Version: 2.4
Name: encoderize
Version: 0.1.1
Summary: A collection of functions to generate various visual representations of text in SVG format
Home-page: https://github.com/DrWheelicus/encoderize
Author: DrWheelicus
Author-email: haydenpmac@gmail.com
License: MIT
Keywords: encoderize,encoder,barcode,svg,visualizer
Classifier: Programming Language :: Python :: 3
Classifier: License :: OSI Approved :: MIT License
Classifier: Operating System :: OS Independent
Requires-Python: >=3.8
License-File: LICENSE
Requires-Dist: svgwrite
Requires-Dist: treepoem
Dynamic: author
Dynamic: author-email
Dynamic: classifier
Dynamic: description
Dynamic: description-content-type
Dynamic: home-page
Dynamic: keywords
Dynamic: license
Dynamic: license-file
Dynamic: requires-dist
Dynamic: requires-python
Dynamic: summary
